Metadata-Version: 1.0
Name: chrisvis
Version: 0.1
Summary: Useful visualizations for Chris
Home-page: UNKNOWN
Author: UNKNOWN
Author-email: UNKNOWN
License: UNKNOWN
Platform: UNKNOWN
